pytest_agent_evals/__init__.py
pytest_agent_evals/_version.py
pytest_agent_evals/chat_agent.py
pytest_agent_evals/foundry_agent.py
pytest_agent_evals/markers.py
pytest_agent_evals/plugin.py
pytest_agent_evals/types.py
pytest_agent_evals-0.0.1b260130.dist-info/entry_points.txt
pytest_agent_evals-0.0.1b260130.dist-info/licenses/LICENSE
pytest_agent_evals-0.0.1b260130.dist-info/WHEEL
pytest_agent_evals-0.0.1b260130.dist-info/METADATA
pytest_agent_evals-0.0.1b260130.dist-info/RECORD
