Metadata-Version: 2.4
Name: pytest-agent-evals
Version: 0.0.1b260130
Summary: Pytest plugin for evaluating AI Agents
Keywords: ai,agent,toolkit,testing,evaluation,pytest
Author-email: Microsoft <aitkfeedback@microsoft.com>
Requires-Python: >=3.10.0
License-Expression: LicenseRef-Microsoft-AI-Toolkit-Pytest-Agent-Evals
Classifier: Development Status :: 4 - Beta
Classifier: Intended Audience :: Developers
Classifier: Operating System :: OS Independent
Classifier: Programming Language :: Python :: 3
Classifier: Programming Language :: Python :: 3.10
Classifier: Programming Language :: Python :: 3.11
Classifier: Programming Language :: Python :: 3.12
Classifier: Programming Language :: Python :: 3.13
Classifier: Programming Language :: Python :: 3.14
Classifier: Topic :: Software Development :: Testing
Classifier: Topic :: Software Development :: Libraries :: Python Modules
Classifier: Typing :: Typed
Classifier: Framework :: Pytest
License-File: LICENSE
Requires-Dist: pytest>=7.0
Requires-Dist: pytest-asyncio>=0.23.0
Requires-Dist: azure-ai-evaluation==1.14.0
Requires-Dist: agent-framework-core>=1.0.0b260116,<=1.0.0b260123
Requires-Dist: agent-framework-azure-ai>=1.0.0b260116,<=1.0.0b260123
Requires-Dist: azure-identity>=1.16.0
Requires-Dist: azure-ai-projects>=2.0.0b3
Requires-Dist: filelock>=3.13.0
Requires-Dist: openai>=1.99.0
Requires-Dist: pydantic>=2,<3
Project-URL: Homepage, https://github.com/microsoft/vscode-ai-toolkit
Project-URL: Issues, https://github.com/microsoft/vscode-ai-toolkit/issues
Project-URL: Repository, https://github.com/microsoft/vscode-ai-toolkit
